ChatGPT2API/V1.py
ChatGPT2API/V3.py
ChatGPT2API/__init__.py
ChatGPT2API/__main__.py
ChatGPT2API/typings.py
ChatGPT2API/utils.py
ChatGPT2API/version.py
ChatGPT2API/config/enable_internet.json
ChatGPT2API-6.8.7.dist-info/LICENSE
ChatGPT2API-6.8.7.dist-info/METADATA
ChatGPT2API-6.8.7.dist-info/WHEEL
ChatGPT2API-6.8.7.dist-info/top_level.txt
ChatGPT2API-6.8.7.dist-info/RECORD
